intermine/__init__.py
intermine/bar_chart.py
intermine/constraints.py
intermine/decorators.py
intermine/errors.py
intermine/idresolution.py
intermine/model.py
intermine/pathfeatures.py
intermine/query.py
intermine/query_manager.py
intermine/registry.py
intermine/results.py
intermine/util.py
intermine/webservice.py
intermine/lists/__init__.py
intermine/lists/list.py
intermine/lists/listmanager.py
intermine-1.13.0.dist-info/LICENSE-BSD
intermine-1.13.0.dist-info/LICENSE-LGPL
intermine-1.13.0.dist-info/METADATA
intermine-1.13.0.dist-info/WHEEL
intermine-1.13.0.dist-info/top_level.txt
intermine-1.13.0.dist-info/RECORD
