Metadata-Version: 2.1
Name: intermine
Version: 1.13.0
Summary: InterMine WebService client
Home-page: http://www.intermine.org
Author: InterMine team
Author-email: all@intermine.org
License: LGPL, BSD
Keywords: webservice,genomic,bioinformatics
Platform: UNKNOWN
Classifier: Programming Language :: Python :: 2.7
Classifier: Programming Language :: Python :: 3
Classifier: Development Status :: 5 - Production/Stable
Classifier: Intended Audience :: Science/Research
Classifier: Intended Audience :: Developers
Classifier: License :: OSI Approved :: GNU Library or Lesser General Public License (LGPL)
Classifier: License :: OSI Approved :: BSD License
Classifier: Topic :: Software Development :: Libraries :: Python Modules
Classifier: Topic :: Internet :: WWW/HTTP
Classifier: Topic :: Scientific/Engineering :: Bio-Informatics
Classifier: Topic :: Scientific/Engineering :: Information Analysis
Classifier: Operating System :: OS Independent
Provides: intermine
License-File: LICENSE-BSD
License-File: LICENSE-LGPL
